{
  "project_info": {
    "project_number": "334547845893",
    "firebase_url": "https://artm-87fc9.firebaseio.com",
    "project_id": "artm-87fc9",
    "storage_bucket": "artm-87fc9.appspot.com"
  },
  "client": [
    {
      "client_info": {
        "mobilesdk_app_id": "1:334547845893:android:a871bf0433cbf5da",
        "android_client_info": {
          "package_name": "alexfragoso.space.rtm"
        }
      },
      "oauth_client": [
        {
          "client_id": "334547845893-rj71f2i05h72i6eegi6bld2ghi51229r.apps.googleusercontent.com",
          "client_type": 1,
          "android_info": {
            "package_name": "alexfragoso.space.rtm",
            "certificate_hash": "51660ebace3021ed5229646da2815c27c325058b"
          }
        },
        {
          "client_id": "334547845893-j8cv5r4254hfj0vprbbljqimmufu1cud.apps.googleusercontent.com",
          "client_type": 3
        }
      ],
      "api_key": [
        {
          "current_key": "AIzaSyBcMgOrb7oWJmShKWOrIZhm7HNZWzPnju0"
        }
      ],
      "services": {
        "appinvite_service": {
          "other_platform_oauth_client": [
            {
              "client_id": "334547845893-j8cv5r4254hfj0vprbbljqimmufu1cud.apps.googleusercontent.com",
              "client_type": 3
            }
          ]
        }
      }
    }
  ],
  "configuration_version": "1"
}